{
  "lurkeranger": {
    "category": "neutral",
    "sounds": [
      {
        "name": "midnightlurker:change",
        "stream": false
      }
    ]
  },
  "lurkerdisappear": {
    "category": "neutral",
    "sounds": [
      {
        "name": "midnightlurker:lurkerdisappear",
        "stream": false
      }
    ]
  },
  "lurkerchase": {
    "category": "neutral",
    "sounds": [
      {
        "name": "midnightlurker:chase",
        "stream": false
      }
    ]
  },
  "lurkerinvisiblejumpscare": {
    "category": "neutral",
    "sounds": [
      {
        "name": "midnightlurker:invisiblejumpscare1",
        "stream": false
      },
      {
        "name": "midnightlurker:invisiblejumpscare2",
        "stream": false
      },
      {
        "name": "midnightlurker:invisiblejumpscare3",
        "stream": false
      }
    ]
  },
  "lurkerchase2": {
    "category": "neutral",
    "sounds": [
      {
        "name": "midnightlurker:chase2",
        "stream": false
      }
    ]
  },
  "lurkerprefinalbreak": {
    "category": "block",
    "sounds": [
      {
        "name": "midnightlurker:prefinalbreak",
        "stream": false
      }
    ]
  },
  "lurkerfinalbreak": {
    "category": "block",
    "sounds": [
      {
        "name": "midnightlurker:finalbreak",
        "stream": false
      }
    ]
  },
  "spookyambience": {
    "category": "record",
    "sounds": [
      {
        "name": "midnightlurker:hal4ambient1",
        "stream": true
      },
      {
        "name": "midnightlurker:hal4ambient3",
        "stream": true
      },
      {
        "name": "midnightlurker:hal4ambient4",
        "stream": true
      },
      {
        "name": "midnightlurker:hal4ambient5",
        "stream": true
      },
      {
        "name": "midnightlurker:hal4ambient6",
        "stream": true
      },
      {
        "name": "midnightlurker:hal4ambient7",
        "stream": true
      },
      {
        "name": "midnightlurker:hal4ambient8",
        "stream": true
      }
    ]
  },
  "insanitygoesbacksound": {
    "category": "neutral",
    "sounds": [
      {
        "name": "midnightlurker:goodrewardsound",
        "stream": false
      },
      {
        "name": "midnightlurker:goodrewardsound1",
        "stream": false
      },
      {
        "name": "midnightlurker:goodrewardsound2",
        "stream": false
      },
      {
        "name": "midnightlurker:goodrewardsound3",
        "stream": false
      },
      {
        "name": "midnightlurker:goodrewardsound4",
        "stream": false
      },
      {
        "name": "midnightlurker:goodrewardsound5",
        "stream": false
      }
    ]
  },
  "insanityambience": {
    "category": "neutral",
    "sounds": [
      {
        "name": "midnightlurker:insanitysounds",
        "stream": false
      }
    ]
  },
  "insanitychase": {
    "category": "neutral",
    "sounds": [
      {
        "name": "midnightlurker:insanitychase",
        "stream": false
      }
    ]
  },
  "lurkerbreakingblock": {
    "category": "block",
    "sounds": [
      {
        "name": "midnightlurker:lurker_break",
        "stream": false
      }
    ]
  },
  "lurkerdistantscream": {
    "category": "neutral",
    "sounds": [
      {
        "name": "midnightlurker:lurker_distant",
        "stream": false
      }
    ]
  },
  "lurkerdeath": {
    "category": "neutral",
    "sounds": [
      {
        "name": "midnightlurker:lurker_death",
        "stream": false
      }
    ]
  },
  "lurkerdeathjumpscare": {
    "category": "neutral",
    "sounds": [
      {
        "name": "midnightlurker:finaljump2",
        "stream": false
      }
    ]
  },
  "lurkerscream": {
    "category": "neutral",
    "sounds": [
      {
        "name": "midnightlurker:lurker_scream1",
        "stream": false
      },
      {
        "name": "midnightlurker:lurker_scream2",
        "stream": false
      },
      {
        "name": "midnightlurker:lurker_scream3",
        "stream": false
      },
      {
        "name": "midnightlurker:lurker_scream4",
        "stream": false
      }
    ]
  },
  "lurkerambient": {
    "category": "hostile",
    "sounds": [
      {
        "name": "midnightlurker:lurker_ambient1",
        "stream": false
      },
      {
        "name": "midnightlurker:lurker_ambient2",
        "stream": false
      },
      {
        "name": "midnightlurker:lurker_ambient3",
        "stream": false
      },
      {
        "name": "midnightlurker:lurker_ambient4",
        "stream": false
      }
    ]
  },
  "lurkerhurt": {
    "category": "hostile",
    "sounds": [
      {
        "name": "midnightlurker:lurker_hurt1",
        "stream": false
      },
      {
        "name": "midnightlurker:lurker_hurt2",
        "stream": false
      },
      {
        "name": "midnightlurker:lurker_hurt3",
        "stream": false
      }
    ]
  },
  "lurkerfootsteps": {
    "category": "hostile",
    "sounds": [
      {
        "name": "midnightlurker:lurker_footstep1",
        "stream": false
      },
      {
        "name": "midnightlurker:lurker_footstep2",
        "stream": false
      },
      {
        "name": "midnightlurker:lurker_footstep3",
        "stream": false
      },
      {
        "name": "midnightlurker:lurker_footstep4",
        "stream": false
      }
    ]
  },
  "lurkerchasesteps": {
    "category": "hostile",
    "sounds": [
      {
        "name": "midnightlurker:lurker_chasestep1",
        "stream": false
      },
      {
        "name": "midnightlurker:lurker_chasestep2",
        "stream": false
      },
      {
        "name": "midnightlurker:lurker_chasestep3",
        "stream": false
      },
      {
        "name": "midnightlurker:lurker_chasestep4",
        "stream": false
      }
    ]
  },
  "lurkerjumpscare": {
    "category": "neutral",
    "sounds": [
      {
        "name": "midnightlurker:finaljump1",
        "stream": false
      },
      {
        "name": "midnightlurker:finaljump3",
        "stream": false
      },
      {
        "name": "midnightlurker:finaljump4",
        "stream": false
      }
    ]
  }
}